{
    "山西": {
        "晋城": {
            "皇城相府": {
                "commentCount": 3746,
                "commentScore": 4.6,
                "coverImageUrl": "https://dimg04.c-ctrip.com/images/100u0z000000nfyq225B1.jpg",
                "distanceStr": "距市中心24.5km",
                "detailUrl": "https://you.ctrip.com/sight/yangcheng2076/51677.html?scene=online",
                "isFree": false,
                "price": 75.0
            },
            "司徒小镇": {
                "commentCount": 531,
                "commentScore": 4.4,
                "coverImageUrl": "https://dimg04.c-ctrip.com/images/100f0r000000hcdx7F9EC.jpg",
                "distanceStr": "距市中心5.3km",
                "detailUrl": "https://you.ctrip.com/sight/jincheng665/1836506.html?scene=online",
                "isFree": false,
                "price": ""
            },
            "王莽岭风景区": {
                "commentCount": 671,
                "commentScore": 4.5,
                "coverImageUrl": "https://dimg04.c-ctrip.com/images/35091e000001f55ov28B8.jpg",
                "distanceStr": "距市中心70.1km",
                "detailUrl": "https://you.ctrip.com/sight/lingchuan3004/51688.html?scene=online",
                "isFree": false,
                "price": 90.0
            },
            "湘峪古堡": {
                "commentCount": 77,
                "commentScore": 4.4,
                "coverImageUrl": "https://dimg04.c-ctrip.com/images/01068120008qjeb4y2DB4.jpg",
                "distanceStr": "距市中心24.8km",
                "detailUrl": "https://you.ctrip.com/sight/qinshui2983/1728718.html?scene=online",
                "isFree": false,
                "price": 65.0
            },
            "郭峪古城": {
                "commentCount": 109,
                "commentScore": 4.0,
                "coverImageUrl": "https://dimg04.c-ctrip.com/images/0102z120009ely4xb0F5B.jpg",
                "distanceStr": "距市中心24.8km",
                "detailUrl": "https://you.ctrip.com/sight/yangcheng2076/5073126.html?scene=online",
                "isFree": false,
                "price": ""
            },
            "大阳古镇": {
                "commentCount": 209,
                "commentScore": 4.5,
                "coverImageUrl": "https://dimg04.c-ctrip.com/images/100j1g000001gzqsxA4A4.jpg",
                "distanceStr": "距市中心20.3km",
                "detailUrl": "https://you.ctrip.com/sight/zezhou3032/2023057.html?scene=online",
                "isFree": false,
                "price": 55.0
            },
            "海会书院": {
                "commentCount": 97,
                "commentScore": 4.7,
                "coverImageUrl": "https://dimg04.c-ctrip.com/images/0103l120008dgg6596783.jpg",
                "distanceStr": "距市中心25.7km",
                "detailUrl": "https://you.ctrip.com/sight/yangcheng2076/1685138.html?scene=online",
                "isFree": false,
                "price": 30.0
            },
            "高平铁佛寺": {
                "commentCount": 6,
                "commentScore": 4.8,
                "coverImageUrl": "https://dimg04.c-ctrip.com/images/1mh4612000fhrx7kuBDDA.jpg",
                "distanceStr": "距市中心32.6km",
                "detailUrl": "https://you.ctrip.com/sight/gaoping3003/144888127.html?scene=online",
                "isFree": true,
                "priceTypeDesc": "免费"
            },
            "云台山风景名胜区": {
                "commentCount": 27843,
                "commentScore": 4.8,
                "coverImageUrl": "https://dimg04.c-ctrip.com/images/1lo1f12000gshh0n9E3EF.jpg",
                "distanceStr": "距晋城52.5km",
                "detailUrl": "https://you.ctrip.com/sight/xiuwu2267/62276.html?scene=online",
                "isFree": false,
                "price": 120.0
            },
            "炎帝陵": {
                "commentCount": 48,
                "commentScore": 4.3,
                "coverImageUrl": "https://dimg04.c-ctrip.com/images/350o1700000113gp7EEEC.jpg",
                "distanceStr": "距市中心47.8km",
                "detailUrl": "https://you.ctrip.com/sight/gaoping3003/51685.html?scene=online",
                "isFree": true,
                "priceTypeDesc": "免费预约"
            },
            "玉皇庙彩塑壁画博物馆": {
                "commentCount": 19,
                "commentScore": 4.7,
                "coverImageUrl": "https://dimg04.c-ctrip.com/images/0103a12000f6dokvf1ECE.jpg",
                "distanceStr": "距市中心10.3km",
                "detailUrl": "https://you.ctrip.com/sight/zezhou3032/51697.html?scene=online",
                "isFree": true,
                "priceTypeDesc": "免费"
            },
            "【晋城】2024箱遇高平音乐节": {
                "commentCount": 0,
                "commentScore": 0.0,
                "coverImageUrl": "https://dimg04.c-ctrip.com/images/0102112000dg6a5404B51.png",
                "distanceStr": "距市中心28.5km",
                "detailUrl": "https://you.ctrip.com/sight/gaoping3003/144972874.html?scene=online",
                "isFree": false,
                "price": ""
            },
            "龙门石窟": {
                "commentCount": 35313,
                "commentScore": 4.7,
                "coverImageUrl": "https://dimg04.c-ctrip.com/images/0102c12000f6sd1co8E56.png",
                "distanceStr": "",
                "detailUrl": "https://you.ctrip.com/sight/luoyang198/8865.html?scene=online",
                "isFree": false,
                "price": 90.0
            },
            "青莲寺": {
                "commentCount": 26,
                "commentScore": 4.5,
                "coverImageUrl": "https://dimg04.c-ctrip.com/images/0106x12000fiahgepDF4F.jpg",
                "distanceStr": "距市中心13.6km",
                "detailUrl": "https://you.ctrip.com/sight/zezhou3032/51699.html?scene=online",
                "isFree": true,
                "priceTypeDesc": "免费"
            },
            "太行山大峡谷": {
                "commentCount": 1824,
                "commentScore": 4.6,
                "coverImageUrl": "https://dimg04.c-ctrip.com/images/100g1800000146ptt52BB.jpg",
                "distanceStr": "距晋城71.5km",
                "detailUrl": "https://you.ctrip.com/sight/huguan1446117/142452.html?scene=online",
                "isFree": false,
                "price": 90.0
            },
            "千年铁魂": {
                "commentCount": 47,
                "commentScore": 4.8,
                "coverImageUrl": "https://dimg04.c-ctrip.com/images/100o1f000001gp48gE8D0.jpg",
                "distanceStr": "距市中心5.5km",
                "detailUrl": "https://you.ctrip.com/sight/jincheng665/2518223.html?scene=online",
                "isFree": false,
                "price": ""
            },
            "华谊兄弟星剧场·重逢晋城": {
                "commentCount": 45,
                "commentScore": 4.8,
                "coverImageUrl": "https://dimg04.c-ctrip.com/images/0101412000f6s42wk33AD.jpg",
                "distanceStr": "距市中心3.1km",
                "detailUrl": "https://you.ctrip.com/sight/jincheng665/133966338.html?scene=online",
                "isFree": false,
                "price": ""
            },
            "玉皇庙": {
                "commentCount": 4,
                "commentScore": 4.0,
                "coverImageUrl": "https://dimg04.c-ctrip.com/images/0100712000cf7qplq5890.jpg",
                "distanceStr": "距市中心4.4km",
                "detailUrl": "https://you.ctrip.com/sight/jincheng665/133838846.html?scene=online",
                "isFree": true,
                "priceTypeDesc": "免费"
            },
            "柳氏民居": {
                "commentCount": 57,
                "commentScore": 4.2,
                "coverImageUrl": "https://dimg04.c-ctrip.com/images/0105w12000f6qwbo9605B.jpg",
                "distanceStr": "距市中心64.0km",
                "detailUrl": "https://you.ctrip.com/sight/qinshui2983/51678.html?scene=online",
                "isFree": false,
                "price": 60.0
            },
            "太行山大峡谷八泉峡景区": {
                "commentCount": 2395,
                "commentScore": 4.5,
                "coverImageUrl": "https://dimg04.c-ctrip.com/images/100j1f000001gpucc5567.jpg",
                "distanceStr": "距晋城82.0km",
                "detailUrl": "https://you.ctrip.com/sight/huguan1446117/1925673.html?scene=online",
                "isFree": false,
                "price": 90.0
            },
            "白马寺": {
                "commentCount": 3067,
                "commentScore": 4.6,
                "coverImageUrl": "https://dimg04.c-ctrip.com/images/10020z000000nqe3v0E1A.jpg",
                "distanceStr": "距晋城88.3km",
                "detailUrl": "https://you.ctrip.com/sight/luoyang198/8940.html?scene=online",
                "isFree": false,
                "price": ""
            },
            "开化寺": {
                "commentCount": 16,
                "commentScore": 4.7,
                "coverImageUrl": "https://dimg04.c-ctrip.com/images/0106p12000f7ffic6BCA9.jpg",
                "distanceStr": "距市中心45.7km",
                "detailUrl": "https://you.ctrip.com/sight/gaoping3003/51701.html?scene=online",
                "isFree": true,
                "priceTypeDesc": "免费"
            },
            "蟒河生态旅游区": {
                "commentCount": 308,
                "commentScore": 4.4,
                "coverImageUrl": "https://dimg04.c-ctrip.com/images/0103x120008s790rf48AD.jpg",
                "distanceStr": "距市中心45.6km",
                "detailUrl": "https://you.ctrip.com/sight/yangcheng2076/51681.html?scene=online",
                "isFree": false,
                "price": 60.0
            },
            "河南宝泉旅游区": {
                "commentCount": 4056,
                "commentScore": 4.4,
                "coverImageUrl": "https://dimg04.c-ctrip.com/images/1lo2i12000cqdc77d6A44.jpg",
                "distanceStr": "距晋城57.6km",
                "detailUrl": "https://you.ctrip.com/sight/huixian2313/72874.html?scene=online",
                "isFree": false,
                "price": 185.0
            },
            "天官王府": {
                "commentCount": 110,
                "commentScore": 4.3,
                "coverImageUrl": "https://dimg04.c-ctrip.com/images/1lo6f12000dwnp0ouC18A.jpg",
                "distanceStr": "距市中心26.7km",
                "detailUrl": "https://you.ctrip.com/sight/yangcheng2076/142554.html?scene=online",
                "isFree": false,
                "price": 36.0
            },
            "隋唐洛阳城国家遗址公园天堂明堂景区": {
                "commentCount": 4540,
                "commentScore": 4.3,
                "coverImageUrl": "https://dimg04.c-ctrip.com/images/0105212000f6t57h842BB.jpg",
                "distanceStr": "距晋城96.8km",
                "detailUrl": "https://you.ctrip.com/sight/luoyang198/126715.html?scene=online",
                "isFree": false,
                "price": 88.0
            },
            "隋唐洛阳城应天门遗址": {
                "commentCount": 1944,
                "commentScore": 4.4,
                "coverImageUrl": "https://dimg04.c-ctrip.com/images/01009120008jb562l1048.png",
                "distanceStr": "距晋城97.3km",
                "detailUrl": "https://you.ctrip.com/sight/luoyang198/5253398.html?scene=online",
                "isFree": false,
                "price": 58.0
            },
            "九女仙湖": {
                "commentCount": 149,
                "commentScore": 4.1,
                "coverImageUrl": "https://dimg04.c-ctrip.com/images/100v1f000001h1dtc6489.jpg",
                "distanceStr": "距市中心28.1km",
                "detailUrl": "https://you.ctrip.com/sight/yangcheng2076/135178.html?scene=online",
                "isFree": false,
                "price": ""
            },
            "锡崖沟挂壁公路": {
                "commentCount": 33,
                "commentScore": 4.5,
                "coverImageUrl": "https://dimg04.c-ctrip.com/images/0106j120008k1h6joFA0C.jpg",
                "distanceStr": "距市中心69.9km",
                "detailUrl": "https://you.ctrip.com/sight/lingchuan3004/124673.html?scene=online",
                "isFree": false,
                "price": ""
            },
            "少林寺": {
                "commentCount": 12348,
                "commentScore": 4.4,
                "coverImageUrl": "https://dimg04.c-ctrip.com/images/010191200087d7pid1736.jpg",
                "distanceStr": "",
                "detailUrl": "https://you.ctrip.com/sight/dengfeng1014/7954.html?scene=online",
                "isFree": false,
                "price": 80.0
            },
            "洛阳博物馆": {
                "commentCount": 2052,
                "commentScore": 4.7,
                "coverImageUrl": "https://dimg04.c-ctrip.com/images/0101a120005ybuydo5E5D.jpg",
                "distanceStr": "",
                "detailUrl": "https://you.ctrip.com/sight/luoyang198/77546.html?scene=online",
                "isFree": true,
                "priceTypeDesc": "免费"
            },
            "再回相府": {
                "commentCount": 84,
                "commentScore": 4.6,
                "coverImageUrl": "https://dimg04.c-ctrip.com/images/0100h12000f6rlmo927C2.jpg",
                "distanceStr": "距市中心24.5km",
                "detailUrl": "https://you.ctrip.com/sight/yangcheng2076/5009419.html?scene=online",
                "isFree": false,
                "price": ""
            },
            "太行锡崖沟旅游度假区": {
                "commentCount": 78,
                "commentScore": 4.5,
                "coverImageUrl": "https://dimg04.c-ctrip.com/images/10051f000001gss2pA09A.jpg",
                "distanceStr": "距市中心69.9km",
                "detailUrl": "https://you.ctrip.com/sight/lingchuan3004/138394.html?scene=online",
                "isFree": false,
                "price": ""
            },
            "隋唐洛阳城九洲池": {
                "commentCount": 837,
                "commentScore": 4.2,
                "coverImageUrl": "https://dimg04.c-ctrip.com/images/0103u12000f6rpeu05A04.jpg",
                "distanceStr": "距晋城97.0km",
                "detailUrl": "https://you.ctrip.com/sight/luoyang198/5630385.html?scene=online",
                "isFree": false,
                "price": 27.0
            },
            "河南博物院": {
                "commentCount": 7347,
                "commentScore": 4.7,
                "coverImageUrl": "https://dimg04.c-ctrip.com/images/350r160000010oixgB0CC.png",
                "distanceStr": "",
                "detailUrl": "https://you.ctrip.com/sight/zhengzhou157/9593.html?scene=online",
                "isFree": true,
                "priceTypeDesc": "免费"
            },
            "洛阳古墓博物馆": {
                "commentCount": 473,
                "commentScore": 4.7,
                "coverImageUrl": "https://dimg04.c-ctrip.com/images/0103812000f6rb49v8C40.jpg",
                "distanceStr": "距晋城93.1km",
                "detailUrl": "https://you.ctrip.com/sight/luoyang198/9337.html?scene=online",
                "isFree": true,
                "priceTypeDesc": "免费"
            },
            "郑州黄河文化公园": {
                "commentCount": 2349,
                "commentScore": 4.3,
                "coverImageUrl": "https://dimg04.c-ctrip.com/images/01055120008k2uu5xCB19.jpg",
                "distanceStr": "距晋城84.6km",
                "detailUrl": "https://you.ctrip.com/sight/zhengzhou157/9603.html?scene=online",
                "isFree": false,
                "price": 45.0
            },
            "晋城博物馆": {
                "commentCount": 52,
                "commentScore": 4.7,
                "coverImageUrl": "https://dimg04.c-ctrip.com/images/0104z120009d44eqc6158.jpg",
                "distanceStr": "距市中心1.5km",
                "detailUrl": "https://you.ctrip.com/sight/jincheng665/1831713.html?scene=online",
                "isFree": true,
                "priceTypeDesc": "免费"
            },
            "武家湾景区": {
                "commentCount": 9,
                "commentScore": 3.8,
                "coverImageUrl": "https://dimg04.c-ctrip.com/images/01028120009d3lp2k0D5D.jpg",
                "distanceStr": "距市中心54.5km",
                "detailUrl": "https://you.ctrip.com/sight/lingchuan3004/5068143.html?scene=online",
                "isFree": false,
                "price": ""
            },
            "寻迹洛神赋": {
                "commentCount": 1237,
                "commentScore": 4.6,
                "coverImageUrl": "https://dimg04.c-ctrip.com/images/1lo4512000d8tsqyf651E.jpg",
                "distanceStr": "",
                "detailUrl": "https://you.ctrip.com/sight/luoyang198/136595037.html?scene=online",
                "isFree": false,
                "price": 215.0
            },
            "新乡南太行旅游度假区": {
                "commentCount": 17,
                "commentScore": 4.2,
                "coverImageUrl": "https://dimg04.c-ctrip.com/images/01024120009hzqpuoD3BA.jpg",
                "distanceStr": "距晋城64.1km",
                "detailUrl": "https://you.ctrip.com/sight/huixian2313/69162079.html?scene=online",
                "isFree": true,
                "priceTypeDesc": "免费"
            },
            "定林寺": {
                "commentCount": 2,
                "commentScore": 5.0,
                "coverImageUrl": "https://dimg04.c-ctrip.com/images/1me2e12000feni50xBDED.jpg",
                "distanceStr": "距市中心34.4km",
                "detailUrl": "https://you.ctrip.com/sight/gaoping3003/5066681.html?scene=online",
                "isFree": false,
                "price": ""
            },
            "八里沟景区": {
                "commentCount": 1263,
                "commentScore": 4.3,
                "coverImageUrl": "https://dimg04.c-ctrip.com/images/350715000000yjy759630.jpg",
                "distanceStr": "距晋城65.5km",
                "detailUrl": "https://you.ctrip.com/sight/huixian2313/72788.html?scene=online",
                "isFree": false,
                "price": 150.0
            },
            "太行1号旅游公路": {
                "commentCount": 1,
                "commentScore": 5.0,
                "coverImageUrl": "https://dimg04.c-ctrip.com/images/01A0s1200093tjrwr5690.jpg",
                "distanceStr": "距市中心64.1km",
                "detailUrl": "https://you.ctrip.com/sight/lingchuan3004/5718401.html?scene=online",
                "isFree": false,
                "price": ""
            },
            "只有河南·戏剧幻城": {
                "commentCount": 3968,
                "commentScore": 4.8,
                "coverImageUrl": "https://dimg04.c-ctrip.com/images/1lo6712000b9w9wqt3763.jpg",
                "distanceStr": "",
                "detailUrl": "https://you.ctrip.com/sight/zhongmu1446088/109563995.html?scene=online",
                "isFree": false,
                "price": 290.0
            },
            "双底村": {
                "commentCount": 2,
                "commentScore": 4.5,
                "coverImageUrl": "https://dimg04.c-ctrip.com/images/1me3412000dvki52l6E8C.jpg",
                "distanceStr": "距市中心55.1km",
                "detailUrl": "https://you.ctrip.com/sight/lingchuan3004/5068140.html?scene=online",
                "isFree": true,
                "priceTypeDesc": "免费"
            },
            "中国国花园": {
                "commentCount": 4126,
                "commentScore": 4.5,
                "coverImageUrl": "https://dimg04.c-ctrip.com/images/0100912000f6t3bxwB808.jpg",
                "distanceStr": "距晋城99.5km",
                "detailUrl": "https://you.ctrip.com/sight/luoyang198/47077.html?scene=online",
                "isFree": true,
                "priceTypeDesc": "免费"
            },
            "万仙山景区": {
                "commentCount": 1568,
                "commentScore": 4.3,
                "coverImageUrl": "https://dimg04.c-ctrip.com/images/350215000000yae095A92.jpg",
                "distanceStr": "距晋城74.4km",
                "detailUrl": "https://you.ctrip.com/sight/huixian2313/72780.html?scene=online",
                "isFree": false,
                "price": 100.0
            },
            "小南村二仙庙": {
                "commentCount": 5,
                "commentScore": 5.0,
                "coverImageUrl": "https://dimg04.c-ctrip.com/images/01A3e120009v2v16p6B11.jpg",
                "distanceStr": "距市中心11.0km",
                "detailUrl": "https://you.ctrip.com/sight/zezhou3032/145378.html?scene=online",
                "isFree": false,
                "price": ""
            },
            "嵩山风景名胜区": {
                "commentCount": 1044,
                "commentScore": 4.5,
                "coverImageUrl": "https://dimg04.c-ctrip.com/images/100o0h0000008zf6aED3A.jpg",
                "distanceStr": "",
                "detailUrl": "https://you.ctrip.com/sight/dengfeng1014/134400.html?scene=online",
                "isFree": false,
                "price": 80.0
            },
            "珏山": {
                "commentCount": 245,
                "commentScore": 4.6,
                "coverImageUrl": "https://dimg04.c-ctrip.com/images/100n1f000001gpbcp86E5.jpg",
                "distanceStr": "距市中心15.0km",
                "detailUrl": "https://you.ctrip.com/sight/zezhou3032/138439.html?scene=online",
                "isFree": false,
                "price": ""
            },
            "龙潭大峡谷": {
                "commentCount": 831,
                "commentScore": 4.5,
                "coverImageUrl": "https://dimg04.c-ctrip.com/images/100k0z000000npqp5EEE2.jpg",
                "distanceStr": "距晋城97.7km",
                "detailUrl": "https://you.ctrip.com/sight/xinan2315/135601.html?scene=online",
                "isFree": false,
                "price": 75.0
            },
            "丽景门景区": {
                "commentCount": 647,
                "commentScore": 4.2,
                "coverImageUrl": "https://dimg04.c-ctrip.com/images/100a10000000pc62478FA.jpg",
                "distanceStr": "距晋城96.4km",
                "detailUrl": "https://you.ctrip.com/sight/luoyang198/47076.html?scene=online",
                "isFree": false,
                "price": 44.0
            },
            "洛邑古城": {
                "commentCount": 240,
                "commentScore": 4.2,
                "coverImageUrl": "https://dimg04.c-ctrip.com/images/0102p1200082niipm17D3.jpg",
                "distanceStr": "距晋城96.1km",
                "detailUrl": "https://you.ctrip.com/sight/luoyang198/2509137.html?scene=online",
                "isFree": true,
                "priceTypeDesc": "免费"
            },
            "太行大峡谷景区": {
                "commentCount": 3542,
                "commentScore": 4.7,
                "coverImageUrl": "https://dimg04.c-ctrip.com/images/1lo5m12000bn80tst8612.jpg",
                "distanceStr": "",
                "detailUrl": "https://you.ctrip.com/sight/linzhou1890/141427.html?scene=online",
                "isFree": false,
                "price": 135.0
            },
            "府城关帝庙": {
                "commentCount": 13,
                "commentScore": 4.5,
                "coverImageUrl": "https://dimg04.c-ctrip.com/images/1me3z12000c0buf9aBD76.jpg",
                "distanceStr": "距市中心10.5km",
                "detailUrl": "https://you.ctrip.com/sight/zezhou3032/1415782.html?scene=online",
                "isFree": true,
                "priceTypeDesc": "免费"
            },
            "通天峡风景区": {
                "commentCount": 879,
                "commentScore": 4.5,
                "coverImageUrl": "https://dimg04.c-ctrip.com/images/350s180000013xuw8EA09.jpg",
                "distanceStr": "",
                "detailUrl": "https://you.ctrip.com/sight/pingshun1446132/126650.html?scene=online",
                "isFree": false,
                "price": 40.0
            },
            "郑州银基动物王国": {
                "commentCount": 2537,
                "commentScore": 4.4,
                "coverImageUrl": "https://dimg04.c-ctrip.com/images/1lo1812000dd3vpec458D.jpg",
                "distanceStr": "",
                "detailUrl": "https://you.ctrip.com/sight/xinmi1163/5709626.html?scene=online",
                "isFree": false,
                "price": 188.0
            },
            "郑州银基国际旅游度假区": {
                "commentCount": 344,
                "commentScore": 4.4,
                "coverImageUrl": "https://dimg04.c-ctrip.com/images/1lo0c12000h4db2o9F8E1.jpg",
                "distanceStr": "",
                "detailUrl": "https://you.ctrip.com/sight/xinmi1163/3392966.html?scene=online",
                "isFree": true,
                "priceTypeDesc": "免费"
            },
            "康百万庄园": {
                "commentCount": 1417,
                "commentScore": 4.6,
                "coverImageUrl": "https://dimg04.c-ctrip.com/images/1A0m13000000u6jhs5735.jpg",
                "distanceStr": "距晋城81.4km",
                "detailUrl": "https://you.ctrip.com/sight/gongyi1846/20817.html?scene=online",
                "isFree": false,
                "price": 48.0
            },
            "长平之战遗址": {
                "commentCount": 16,
                "commentScore": 4.0,
                "coverImageUrl": "https://dimg04.c-ctrip.com/images/0102512000awunk5e0605.jpg",
                "distanceStr": "距市中心41.8km",
                "detailUrl": "https://you.ctrip.com/sight/gaoping3003/69343077.html?scene=online",
                "isFree": false,
                "price": ""
            },
            "红豆杉大峡谷": {
                "commentCount": 13,
                "commentScore": 4.2,
                "coverImageUrl": "https://dimg04.c-ctrip.com/images/0106k120008s79crhED22.jpg",
                "distanceStr": "距市中心55.4km",
                "detailUrl": "https://you.ctrip.com/sight/lingchuan3004/1415592.html?scene=online",
                "isFree": false,
                "price": ""
            },
            "砥洎城": {
                "commentCount": 21,
                "commentScore": 4.1,
                "coverImageUrl": "https://dimg04.c-ctrip.com/images/100d1f000001gorzh7B2A.jpg",
                "distanceStr": "距市中心29.4km",
                "detailUrl": "https://you.ctrip.com/sight/yangcheng2076/51686.html?scene=online",
                "isFree": false,
                "price": ""
            },
            "良户古村": {
                "commentCount": 4,
                "commentScore": 4.3,
                "coverImageUrl": "https://dimg04.c-ctrip.com/images/0106v12000f6tjjc8C799.jpg",
                "distanceStr": "距市中心30.0km",
                "detailUrl": "https://you.ctrip.com/sight/gaoping3003/130368726.html?scene=online",
                "isFree": false,
                "price": ""
            },
            "唐宫乐宴": {
                "commentCount": 119,
                "commentScore": 4.3,
                "coverImageUrl": "https://dimg04.c-ctrip.com/images/1lo6y12000dknywrdC44F.jpg",
                "distanceStr": "距晋城97.3km",
                "detailUrl": "https://you.ctrip.com/sight/luoyang198/144931182.html?scene=online",
                "isFree": false,
                "price": ""
            },
            "二里头夏都遗址博物馆": {
                "commentCount": 128,
                "commentScore": 4.6,
                "coverImageUrl": "https://dimg04.c-ctrip.com/images/01062120008h3quw0516A.jpg",
                "distanceStr": "距晋城91.0km",
                "detailUrl": "https://you.ctrip.com/sight/luoyang198/5675368.html?scene=online",
                "isFree": true,
                "priceTypeDesc": "免费"
            },
            "打铁花": {
                "commentCount": 0,
                "commentScore": 0.0,
                "coverImageUrl": "https://dimg04.c-ctrip.com/images/0101h12000evgmt8t4FA0.jpg",
                "distanceStr": "距市中心5.5km",
                "detailUrl": "https://you.ctrip.com/sight/jincheng665/145611511.html?scene=online",
                "isFree": false,
                "price": ""
            },
            "陟椒三教堂": {
                "commentCount": 1,
                "commentScore": 5.0,
                "coverImageUrl": "https://dimg04.c-ctrip.com/images/0104i1200097hoecw9EEF.jpg",
                "distanceStr": "距市中心21.2km",
                "detailUrl": "https://you.ctrip.com/sight/zezhou3032/1415558.html?scene=online",
                "isFree": true,
                "priceTypeDesc": "免费"
            },
            "中原福塔": {
                "commentCount": 2937,
                "commentScore": 4.7,
                "coverImageUrl": "https://dimg04.c-ctrip.com/images/010691200082cli2sE99D.jpg",
                "distanceStr": "",
                "detailUrl": "https://you.ctrip.com/sight/zhengzhou157/119168.html?scene=online",
                "isFree": false,
                "price": 98.0
            },
            "隋唐城遗址植物园": {
                "commentCount": 2139,
                "commentScore": 4.7,
                "coverImageUrl": "https://dimg04.c-ctrip.com/images/35021f000001g50o71595.jpg",
                "distanceStr": "",
                "detailUrl": "https://you.ctrip.com/sight/luoyang198/1409396.html?scene=online",
                "isFree": true,
                "priceTypeDesc": "免费"
            },
            "昆山挂壁公路": {
                "commentCount": 2,
                "commentScore": 5.0,
                "coverImageUrl": "https://dimg04.c-ctrip.com/images/0102212000f0ft3to6F1F.jpg",
                "distanceStr": "距市中心70.7km",
                "detailUrl": "https://you.ctrip.com/sight/lingchuan3004/145612822.html?scene=online",
                "isFree": false,
                "price": ""
            },
            "清明上河园": {
                "commentCount": 13955,
                "commentScore": 4.5,
                "coverImageUrl": "https://dimg04.c-ctrip.com/images/350g160000010qachB11D.jpg",
                "distanceStr": "",
                "detailUrl": "https://you.ctrip.com/sight/kaifeng165/9504.html?scene=online",
                "isFree": false,
                "price": 120.0
            },
            "七彩太行云上滑雪场": {
                "commentCount": 3,
                "commentScore": 5.0,
                "coverImageUrl": "https://dimg04.c-ctrip.com/images/1lo4z12000gaepykb6166.jpg",
                "distanceStr": "距市中心62.1km",
                "detailUrl": "https://you.ctrip.com/sight/lingchuan3004/135940002.html?scene=online",
                "isFree": false,
                "price": ""
            },
            "七彩太行旅游度假区": {
                "commentCount": 0,
                "commentScore": 0.0,
                "coverImageUrl": "https://dimg04.c-ctrip.com/images/0HJ4u12000g2v46sdF4C6.jpg",
                "distanceStr": "距市中心62.1km",
                "detailUrl": "https://you.ctrip.com/sight/lingchuan3004/145426031.html?scene=online",
                "isFree": false,
                "price": ""
            },
            "郑州海洋馆": {
                "commentCount": 4338,
                "commentScore": 4.4,
                "coverImageUrl": "https://dimg04.c-ctrip.com/images/1lo3h12000banx8tqA5FC.jpg",
                "distanceStr": "",
                "detailUrl": "https://you.ctrip.com/sight/zhengzhou157/143225.html?scene=online",
                "isFree": false,
                "price": 159.0
            },
            "洛阳隋唐大运河文化博物馆": {
                "commentCount": 113,
                "commentScore": 4.5,
                "coverImageUrl": "https://dimg04.c-ctrip.com/images/0101o12000h14gxem6358.jpg",
                "distanceStr": "距晋城96.5km",
                "detailUrl": "https://you.ctrip.com/sight/luoyang198/9358.html?scene=online",
                "isFree": true,
                "priceTypeDesc": "免费"
            },
            "济源黄河小浪底风景区": {
                "commentCount": 238,
                "commentScore": 4.4,
                "coverImageUrl": "https://dimg04.c-ctrip.com/images/100s0q000000giarfAF9F.jpg",
                "distanceStr": "距晋城76.2km",
                "detailUrl": "https://you.ctrip.com/sight/jiyuan640/20841.html?scene=online",
                "isFree": false,
                "price": ""
            },
            "黄河小浪底水利枢纽风景区": {
                "commentCount": 317,
                "commentScore": 4.3,
                "coverImageUrl": "https://dimg04.c-ctrip.com/images/100s0q000000giarfAF9F.jpg",
                "distanceStr": "距晋城76.2km",
                "detailUrl": "https://you.ctrip.com/sight/jiyuan640/1832329.html?scene=online",
                "isFree": false,
                "price": 38.0
            },
            "关林庙": {
                "commentCount": 1114,
                "commentScore": 4.4,
                "coverImageUrl": "https://dimg04.c-ctrip.com/images/100k0f0000007ex9j70C7.jpg",
                "distanceStr": "",
                "detailUrl": "https://you.ctrip.com/sight/luoyang198/141428.html?scene=online",
                "isFree": false,
                "price": 39.19
            },
            "太行人家喜镇苏庄": {
                "commentCount": 3,
                "commentScore": 5.0,
                "coverImageUrl": "https://dimg04.c-ctrip.com/images/0100n12000dohe4clFF42.jpg",
                "distanceStr": "距市中心27.6km",
                "detailUrl": "https://you.ctrip.com/sight/gaoping3003/136049422.html?scene=online",
                "isFree": true,
                "priceTypeDesc": "免费"
            },
            "岱庙": {
                "commentCount": 7,
                "commentScore": 4.0,
                "coverImageUrl": "https://dimg04.c-ctrip.com/images/0103t1200087fftds6AAB.jpg",
                "distanceStr": "距市中心13.6km",
                "detailUrl": "https://you.ctrip.com/sight/zezhou3032/1415684.html?scene=online",
                "isFree": true,
                "priceTypeDesc": "免费"
            },
            "白马寺山森林公园": {
                "commentCount": 32,
                "commentScore": 4.7,
                "coverImageUrl": "https://dimg04.c-ctrip.com/images/1me3v12000bycaf766BF9.jpg",
                "distanceStr": "距市中心6.6km",
                "detailUrl": "https://you.ctrip.com/sight/jincheng665/51679.html?scene=online",
                "isFree": false,
                "price": ""
            },
            "广胜寺": {
                "commentCount": 958,
                "commentScore": 4.7,
                "coverImageUrl": "https://dimg04.c-ctrip.com/images/1lo5j12000d2vh7o91CD4.jpg",
                "distanceStr": "",
                "detailUrl": "https://you.ctrip.com/sight/hongtong3015/11391.html?scene=online",
                "isFree": false,
                "price": 68.0
            },
            "天子驾六博物馆": {
                "commentCount": 1733,
                "commentScore": 4.4,
                "coverImageUrl": "https://dimg04.c-ctrip.com/images/0102t12000h0gkyn25C86.jpg",
                "distanceStr": "距晋城98.1km",
                "detailUrl": "https://you.ctrip.com/sight/luoyang198/47087.html?scene=online",
                "isFree": false,
                "price": ""
            },
            "崇明寺": {
                "commentCount": 2,
                "commentScore": 5.0,
                "coverImageUrl": "https://dimg04.c-ctrip.com/images/1mh3f12000flh5or21D62.jpg",
                "distanceStr": "距市中心33.5km",
                "detailUrl": "https://you.ctrip.com/sight/gaoping3003/5066680.html?scene=online",
                "isFree": false,
                "price": ""
            },
            "西溪二仙庙": {
                "commentCount": 0,
                "commentScore": 0.0,
                "coverImageUrl": "https://dimg04.c-ctrip.com/images/0HJ1m12000g606tay6C6D.jpg",
                "distanceStr": "距市中心47.6km",
                "detailUrl": "https://you.ctrip.com/sight/lingchuan3004/133548441.html?scene=online",
                "isFree": false,
                "price": ""
            },
            "建业电影小镇": {
                "commentCount": 5361,
                "commentScore": 4.6,
                "coverImageUrl": "https://dimg04.c-ctrip.com/images/350j1a0000018vlleBC8A.jpg",
                "distanceStr": "",
                "detailUrl": "https://you.ctrip.com/sight/zhongmu1446088/5620391.html?scene=online",
                "isFree": false,
                "price": 69.9
            },
            "郑州方特旅游度假区": {
                "commentCount": 146,
                "commentScore": 4.7,
                "coverImageUrl": "https://dimg04.c-ctrip.com/images/10021f000001gxer081B9.jpg",
                "distanceStr": "",
                "detailUrl": "https://you.ctrip.com/sight/zhongmu1446088/4379348.html?scene=online",
                "isFree": false,
                "price": 199.0
            },
            "万岁山武侠城": {
                "commentCount": 9812,
                "commentScore": 4.7,
                "coverImageUrl": "https://dimg04.c-ctrip.com/images/0105812000f6qvr21C3FB.jpg",
                "distanceStr": "",
                "detailUrl": "https://you.ctrip.com/sight/kaifeng165/77323.html?scene=online",
                "isFree": false,
                "price": 74.0
            }
        }
    }
}